animatplot/__init__.py
animatplot/_version.py
animatplot/animation.py
animatplot/timeline.py
animatplot/util.py
animatplot/animations/__init__.py
animatplot/animations/vectors.py
animatplot/blocks/__init__.py
animatplot/blocks/base.py
animatplot/blocks/image_like.py
animatplot/blocks/lineplots.py
animatplot/blocks/surface.py
animatplot/blocks/title.py
animatplot/blocks/update.py
animatplot/blocks/vectors.py
animatplot_ng-0.4.5.dist-info/licenses/LICENSE
animatplot_ng-0.4.5.dist-info/METADATA
animatplot_ng-0.4.5.dist-info/WHEEL
animatplot_ng-0.4.5.dist-info/top_level.txt
animatplot_ng-0.4.5.dist-info/RECORD
