Metadata-Version: 2.4
Name: animatplot-ng
Version: 0.4.5
Summary: Making animating in matplotlib easy
Home-page: https://github.com/boutproject/animatplot-ng/
Author: Tyler Makaro
Author-email: 
License: MIT
Classifier: Intended Audience :: Education
Classifier: Intended Audience :: Science/Research
Classifier: License :: OSI Approved :: MIT License
Classifier: Programming Language :: Python :: 3 :: Only
Classifier: Programming Language :: Python :: 3.5
Classifier: Programming Language :: Python :: 3.6
Classifier: Programming Language :: Python :: 3.7
Classifier: Topic :: Scientific/Engineering :: Visualization
Requires-Python: >=3.5
License-File: LICENSE
Requires-Dist: matplotlib>=2.2
Dynamic: author
Dynamic: classifier
Dynamic: description
Dynamic: description-content-type
Dynamic: home-page
Dynamic: license
Dynamic: license-file
Dynamic: requires-dist
Dynamic: requires-python
Dynamic: summary
